{
	"info": {
		"_postman_id": "70e165c2-d80b-4145-a380-54dd30949332",
		"name": "group_23",
		"schema": "https://schema.getpostman.com/json/collection/v2.1.0/collection.json"
	},
	"item": [
		{
			"name": "ER_1",
			"protocolProfileBehavior": {
				"followOriginalHttpMethod": false
			},
			"request": {
				"method": "GET",
				"header": [],
				"url": {
					"raw": "162.55.220.72:5005/get_method?name=str&age=int",
					"host": [
						"162",
						"55",
						"220",
						"72"
					],
					"port": "5005",
					"path": [
						"get_method"
					],
					"query": [
						{
							"key": "name",
							"value": "str"
						},
						{
							"key": "age",
							"value": "int"
						}
					]
				}
			},
			"response": []
		},
		{
			"name": "ER_2",
			"request": {
				"method": "POST",
				"header": [],
				"body": {
					"mode": "formdata",
					"formdata": [
						{
							"key": "name",
							"value": "tina",
							"type": "text"
						},
						{
							"key": "age",
							"value": "27",
							"type": "text"
						},
						{
							"key": "salary",
							"value": "25000",
							"type": "text"
						}
					]
				},
				"url": {
					"raw": "162.55.220.72:5005/user_info_3",
					"host": [
						"162",
						"55",
						"220",
						"72"
					],
					"port": "5005",
					"path": [
						"user_info_3"
					]
				}
			},
			"response": []
		},
		{
			"name": "ER_3",
			"request": {
				"method": "GET",
				"header": [],
				"url": {
					"raw": "162.55.220.72:5005/object_info_1?name=Tina&age=27&weight=68",
					"host": [
						"162",
						"55",
						"220",
						"72"
					],
					"port": "5005",
					"path": [
						"object_info_1"
					],
					"query": [
						{
							"key": "name",
							"value": "Tina"
						},
						{
							"key": "age",
							"value": "27"
						},
						{
							"key": "weight",
							"value": "68"
						}
					]
				}
			},
			"response": []
		},
		{
			"name": "ER_4",
			"request": {
				"method": "GET",
				"header": [],
				"url": {
					"raw": "162.55.220.72:5005/object_info_2?name=Tina&age=27&salary=25000",
					"host": [
						"162",
						"55",
						"220",
						"72"
					],
					"port": "5005",
					"path": [
						"object_info_2"
					],
					"query": [
						{
							"key": "name",
							"value": "Tina"
						},
						{
							"key": "age",
							"value": "27"
						},
						{
							"key": "salary",
							"value": "25000"
						}
					]
				}
			},
			"response": []
		},
		{
			"name": "ER_5",
			"request": {
				"method": "GET",
				"header": [],
				"url": {
					"raw": "162.55.220.72:5005/object_info_3?name=tina&age=27&salary=25000",
					"host": [
						"162",
						"55",
						"220",
						"72"
					],
					"port": "5005",
					"path": [
						"object_info_3"
					],
					"query": [
						{
							"key": "name",
							"value": "tina"
						},
						{
							"key": "age",
							"value": "27"
						},
						{
							"key": "salary",
							"value": "25000"
						}
					]
				}
			},
			"response": []
		},
		{
			"name": "ER_6",
			"request": {
				"method": "GET",
				"header": [],
				"url": {
					"raw": "162.55.220.72:5005/object_info_4?name=Tina&age=27&salary=25000",
					"host": [
						"162",
						"55",
						"220",
						"72"
					],
					"port": "5005",
					"path": [
						"object_info_4"
					],
					"query": [
						{
							"key": "name",
							"value": "Tina"
						},
						{
							"key": "age",
							"value": "27"
						},
						{
							"key": "salary",
							"value": "25000"
						}
					]
				}
			},
			"response": []
		},
		{
			"name": "New Request",
			"request": {
				"method": "POST",
				"header": [],
				"body": {
					"mode": "formdata",
					"formdata": [
						{
							"key": "name",
							"value": "Tina",
							"type": "text"
						},
						{
							"key": "age",
							"value": "27",
							"type": "text"
						},
						{
							"key": "salary",
							"value": "25000",
							"type": "text"
						}
					]
				},
				"url": {
					"raw": "162.55.220.72:5005/user_info_2",
					"host": [
						"162",
						"55",
						"220",
						"72"
					],
					"port": "5005",
					"path": [
						"user_info_2"
					]
				}
			},
			"response": []
		}
	]
}